Workbook

Sheet How to use
B1: Mystery Shopper Improvement Tracker
B2: Purpose: track every improvement point from Mystery Shopper reports until it is fixed and checked. Set up after the QA internal audit (auditor: Dr. Shen, September 2026).
B4: THE CYCLE (every report)
B5: 1. New report | C5: Log it in 'MS Reports'. Then add each improvement point to 'Tracker' (one row per point). Status = Open.
B6: 2. Review meeting | C6: For each Open point, agree the action plan, PIC, priority and timeline. Type the 'Date agreed'. The target date fills in by itself.
B7: 3. Follow up | C7: At every meeting, update Status and Progress. Look at the Alert column first: red OVERDUE, then amber Due soon.
B8: 4. Done | C8: When the action is finished, set Status to 'Done - to verify'. Fill in Date completed and Evidence (e.g. SOP updated, training attendance, new WhatsApp template).
B9: 5. Verify & close | C9: Check the next Mystery Shopper report for that outlet. Not mentioned again: set Status to 'Closed' and fill in Verified by / date. Mentioned again: set it back to 'In progress' and revise the plan.
B10: 6. Record the meeting | C10: Add one row in 'Meeting Log' (date, attendees, IDs reviewed, decisions).
B12: PRIORITY & TIMELINE GUIDE (agree the real timeline at the meeting)
B13: High | C13: Affects trust or whether the customer comes back (e.g. sales pressure, long waiting). Aim: within 2 weeks.
B14: Medium | C14: Affects comfort or clarity (e.g. treatment steps, technique). Aim: within 1 month.
B15: Low | C15: Small preference or quick fix (e.g. reminder by WhatsApp). Aim: within 1 to 2 months.
B17: STATUS
B18: Open | C18: Logged, no action agreed yet.
B19: In progress | C19: Action plan agreed and being done.
B20: Done - to verify | C20: Action finished. Waiting for the next MS report to confirm it worked.
B21: Closed | C21: Verified: the problem did not come back. The row turns grey.
B22: On hold | C22: Paused on purpose (write the reason in Remarks).
B24: ALERT COLUMN (automatic)
B25: OVERDUE | C25: Target date has passed and it is not done yet. Discuss first.
B26: Due soon | C26: Target date is within the next 7 days.
B27: On track | C27: Target date is more than 7 days away.
B28: Set target | C28: No target yet: pick a timeline and date agreed.
B30: CELLS
B31: White | C31: Type here.
B32: Grey | C32: Automatic (formulas). Don't type, except the target date if you need a custom date.
B34: ID FORMAT
C35: MS-YYMM-OUTLET-NN e.g. MS-2609-CLM-01 = Mystery Shopper, Sep 2026, Cheras Leisure Mall, point 1. Outlet codes are in the Lists sheet (GL, PC, CLM).
B37: EXAMPLE ROW (example only, not real data: shows how a finished row looks)
B38: ID | C38: MS-2610-PC-01
B39: Outlet | C39: Puchong
B40: Improvement point | C40: Customer not reminded of simple actions during treatment
B41: Priority | C41: Medium
B42: Agreed action plan | C42: Add 3 short cue phrases to the therapist script; brief all therapists at the morning huddle
B43: PIC | C43: Therapist Lead
B44: Date agreed / Timeline | C44: 01/10/2026 · 2 weeks → Target date 15/10/2026 (auto)
B45: Status / Progress | C45: Done - to verify · Script updated 07/10; all 4 therapists briefed 08/10
B46: Evidence | C46: Updated script v2 + huddle attendance sheet
B47: How to verify | C47: Next MS report for Puchong: point not mentioned again

Sheet Tracker
A1: Mystery Shopper Improvement Tracker
A2: One row per improvement point. White cells: type here. Grey cells: automatic, don't type. Set up after the QA internal audit (auditor: Dr. Shen) to track each Mystery Shopper improvement point until it is fixed and verified.
A3: ① FEEDBACK (from the Mystery Shopper report) | I3: ② ACTION PLAN (agree at the review meeting) | O3: ③ FOLLOW-UP (update at every review) | U3: ④ VERIFY & CLOSE
A4: ID | B4: Outlet | C4: Improvement point | D4: MS report (month) | E4: Category | F4: What the customer said | G4: Customer's original words | H4: Suggested action (from report / draft) | I4: Priority | J4: Agreed action plan | K4: PIC | L4: Date agreed | M4: Timeline | N4: Target date (auto) | O4: Status | P4: Days left (auto) | Q4: Alert (auto) | R4: Progress update / action taken | S4: Date completed | T4: Evidence | U4: How to verify | V4: Verified by | W4: Verified date | X4: Remarks
A5: MS-2609-CLM-01 | B5: Cheras Leisure Mall | C5: Package presentation felt too commercial | D5: Sep 2026 | E5: Sales & package | F5: Customer was first shown a full treatment journey above RM20,000, then a package recommendation. She felt pressured and the number itself was intimidating. This is the main reason her revisit answer was only "Maybe". | G5: “先给我看整个疗程2万多，然后推荐配套。过程有点压力，也被数值吓到。如果有菜单直接看更好。” | H5: Show a simple treatment menu early, before any package talk, to reduce sticker shock and make options easier to understand. | I5: High | N5: =IF(OR(L5="",M5=""),"",L5+IFERROR(VLOOKUP(M5,Lists!$G$3:$H$20,2,FALSE()),0)) | O5: Open | P5: =IF(OR(N5="",O5="Closed",O5="Done - to verify"),"",N5-TODAY()) | Q5: =IF(C5="","",IF(O5="Closed","Closed",IF(O5="Done - to verify","To verify",IF(O5="On hold","On hold",IF(N5="","Set target",IF(N5<TODAY(),"OVERDUE",IF(N5-TODAY()<=7,"Due soon","On track"))))))) -> Set target | U5: Next MS report: customer does not mention sales pressure; revisit answer improves. | X5: Same theme as MS-2609-GL-01 (consultant sales approach).
A6: MS-2609-CLM-02 | B6: Cheras Leisure Mall | C6: Customer had to keep confirming the RM399 trial | D6: Sep 2026 | E6: Sales & package | F6: Customer needed to confirm several times that she was doing the RM399 trial. Clear reassurance at the start would help her feel secure. | G6: “我需要反复确认是不是给我399trial配套，他们可能可以说我今天是做这个价钱，让我安心。” | H6: Confirm today's RM399 trial clearly at the start, before any upgrade conversation. | I6: High | N6: =IF(OR(L6="",M6=""),"",L6+IFERROR(VLOOKUP(M6,Lists!$G$3:$H$20,2,FALSE()),0)) | O6: Open | P6: =IF(OR(N6="",O6="Closed",O6="Done - to verify"),"",N6-TODAY()) | Q6: =IF(C6="","",IF(O6="Closed","Closed",IF(O6="Done - to verify","To verify",IF(O6="On hold","On hold",IF(N6="","Set target",IF(N6<TODAY(),"OVERDUE",IF(N6-TODAY()<=7,"Due soon","On track"))))))) -> Set target | U6: Next MS report for Cheras Leisure Mall: this point is not mentioned again.
A7: MS-2609-CLM-03 | B7: Cheras Leisure Mall | C7: Treatment steps were not clear | D7: Sep 2026 | E7: Communication | F7: She heard a lot about acne-scar packages but was not clear on the steps for that visit. After the laser she thought it was finished, then learned there was a hydration treatment too. | G7: “在开始疗程的时候我不清楚我的疗程的步骤……做完laser我以为完了，医生告诉我还有补水护理。” | H7: Brief the full treatment flow from start to finish before treatment starts. | I7: Medium | N7: =IF(OR(L7="",M7=""),"",L7+IFERROR(VLOOKUP(M7,Lists!$G$3:$H$20,2,FALSE()),0)) | O7: Open | P7: =IF(OR(N7="",O7="Closed",O7="Done - to verify"),"",N7-TODAY()) | Q7: =IF(C7="","",IF(O7="Closed","Closed",IF(O7="Done - to verify","To verify",IF(O7="On hold","On hold",IF(N7="","Set target",IF(N7<TODAY(),"OVERDUE",IF(N7-TODAY()<=7,"Due soon","On track"))))))) -> Set target | U7: Next MS report for Cheras Leisure Mall: this point is not mentioned again.
A8: MS-2609-CLM-04 | B8: Cheras Leisure Mall | C8: Long waiting time (about 1pm to 4pm) | D8: Sep 2026 | E8: Waiting & process flow | F8: Customer stayed about 3 hours. Waiting at face washing / photos, doctor, payment (bill printing) and account setup. | G8: “整体时长我在那边呆了1pm到差不多4pm，感觉时间比较久……尤其是付款等打单等了蛮久。” | H8: Tighten handoffs between washing, photos, doctor, payment and registration. | I8: High | N8: =IF(OR(L8="",M8=""),"",L8+IFERROR(VLOOKUP(M8,Lists!$G$3:$H$20,2,FALSE()),0)) | O8: Open | P8: =IF(OR(N8="",O8="Closed",O8="Done - to verify"),"",N8-TODAY()) | Q8: =IF(C8="","",IF(O8="Closed","Closed",IF(O8="Done - to verify","To verify",IF(O8="On hold","On hold",IF(N8="","Set target",IF(N8<TODAY(),"OVERDUE",IF(N8-TODAY()<=7,"Due soon","On track"))))))) -> Set target | U8: Next MS report: total visit time is shorter and waiting is not mentioned.
A9: MS-2609-CLM-05 | B9: Cheras Leisure Mall | C9: Registration code sent without explanation | D9: Sep 2026 | E9: Registration & system | F9: A code was sent for account registration without first explaining why. The customer found it strange until the purpose was clarified. | G9: “有人来说要拿code注册账号，一开始没和我解释是为了这个目的……我感到奇怪。” | H9: Explain why the customer is receiving the code before sending it. | I9: Low | N9: =IF(OR(L9="",M9=""),"",L9+IFERROR(VLOOKUP(M9,Lists!$G$3:$H$20,2,FALSE()),0)) | O9: Open | P9: =IF(OR(N9="",O9="Closed",O9="Done - to verify"),"",N9-TODAY()) | Q9: =IF(C9="","",IF(O9="Closed","Closed",IF(O9="Done - to verify","To verify",IF(O9="On hold","On hold",IF(N9="","Set target",IF(N9<TODAY(),"OVERDUE",IF(N9-TODAY()<=7,"Due soon","On track"))))))) -> Set target | U9: Next MS report for Cheras Leisure Mall: this point is not mentioned again.
A10: MS-2609-CLM-06 | B10: Cheras Leisure Mall | C10: Therapist hand technique felt firm | D10: Sep 2026 | E10: Treatment & technique | F10: Therapist explained the steps and cared for the customer (offered to switch off the light), but the hand technique felt slightly firm. | G10: “护理小姐姐的手法可以再进步，手法不够柔。” | H10: Use a gentler, more relaxing hand technique (refresher training). | I10: Medium | N10: =IF(OR(L10="",M10=""),"",L10+IFERROR(VLOOKUP(M10,Lists!$G$3:$H$20,2,FALSE()),0)) | O10: Open | P10: =IF(OR(N10="",O10="Closed",O10="Done - to verify"),"",N10-TODAY()) | Q10: =IF(C10="","",IF(O10="Closed","Closed",IF(O10="Done - to verify","To verify",IF(O10="On hold","On hold",IF(N10="","Set target",IF(N10<TODAY(),"OVERDUE",IF(N10-TODAY()<=7,"Due soon","On track"))))))) -> Set target | U10: Next MS report for Cheras Leisure Mall: this point is not mentioned again.
A11: MS-2609-CLM-07 | B11: Cheras Leisure Mall | C11: Prefers WhatsApp reminder instead of a call | D11: Sep 2026 | E11: Appointment & reminder | F11: Outlet proactively sent the address and called the day before (good). But the customer was at work and would prefer a WhatsApp reminder. | G11: “前一天会call。不过我在工作，希望whatsapp reminder就好。” | H11: Draft: ask customers their preferred reminder method (WhatsApp or call) and follow it. | I11: Low | N11: =IF(OR(L11="",M11=""),"",L11+IFERROR(VLOOKUP(M11,Lists!$G$3:$H$20,2,FALSE()),0)) | O11: Open | P11: =IF(OR(N11="",O11="Closed",O11="Done - to verify"),"",N11-TODAY()) | Q11: =IF(C11="","",IF(O11="Closed","Closed",IF(O11="Done - to verify","To verify",IF(O11="On hold","On hold",IF(N11="","Set target",IF(N11<TODAY(),"OVERDUE",IF(N11-TODAY()<=7,"Due soon","On track"))))))) -> Set target | U11: Next MS report for Cheras Leisure Mall: this point is not mentioned again.
A12: MS-2609-GL-01 | B12: Greenlane | C12: Service attitude dropped when customer could not afford the high-price package | D12: Sep 2026 | E12: Service attitude | F12: Customer felt clear snobbery and discrimination because she had no credit card and a limited budget. After staff learned she could not buy the high-price package (RM30k), their service attitude dropped and she was disappointed. She asked why there were no other options based on the customer's needs, instead of only pushing high-price packages. In her follow-up message she said it was not only the selling: mainly the attitude made her uncomfortable. She added that young staff lacking experience is understandable, as long as they are willing to improve. | G12: “感受到有明显的势利感和歧视倾向（因为我没有信用卡而且预算有限），服务员在得知无法消费高额配套(RM 30k)，而产生服务态度的落差，有点失望。怎么就没有其他选择‘满足客户需求’为导向，而非一味推销高价配套呢！” Follow-up: “其实当天不完全是因为推销的问题，主要是态度，让人感觉不太舒服。” | H12: Draft: coach the consultation team to keep the same warm service whatever the customer's budget, and to offer options that fit the customer's needs and budget instead of only high-price packages. | I12: High | N12: =IF(OR(L12="",M12=""),"",L12+IFERROR(VLOOKUP(M12,Lists!$G$3:$H$20,2,FALSE()),0)) | O12: Open | P12: =IF(OR(N12="",O12="Closed",O12="Done - to verify"),"",N12-TODAY()) | Q12: =IF(C12="","",IF(O12="Closed","Closed",IF(O12="Done - to verify","To verify",IF(O12="On hold","On hold",IF(N12="","Set target",IF(N12<TODAY(),"OVERDUE",IF(N12-TODAY()<=7,"Due soon","On track"))))))) -> Set target | U12: Next MS report for Greenlane: no comments on attitude or sales pressure; customer is offered options within budget. | X12: Same theme as MS-2609-CLM-01 and -02 (consultant sales approach). Feedback received 15/09/2026.
N13: =IF(OR(L13="",M13=""),"",L13+IFERROR(VLOOKUP(M13,Lists!$G$3:$H$20,2,FALSE()),0)) | P13: =IF(OR(N13="",O13="Closed",O13="Done - to verify"),"",N13-TODAY()) | Q13: =IF(C13="","",IF(O13="Closed","Closed",IF(O13="Done - to verify","To verify",IF(O13="On hold","On hold",IF(N13="","Set target",IF(N13<TODAY(),"OVERDUE",IF(N13-TODAY()<=7,"Due soon","On track")))))))
N14: =IF(OR(L14="",M14=""),"",L14+IFERROR(VLOOKUP(M14,Lists!$G$3:$H$20,2,FALSE()),0)) | P14: =IF(OR(N14="",O14="Closed",O14="Done - to verify"),"",N14-TODAY()) | Q14: =IF(C14="","",IF(O14="Closed","Closed",IF(O14="Done - to verify","To verify",IF(O14="On hold","On hold",IF(N14="","Set target",IF(N14<TODAY(),"OVERDUE",IF(N14-TODAY()<=7,"Due soon","On track")))))))
N15: =IF(OR(L15="",M15=""),"",L15+IFERROR(VLOOKUP(M15,Lists!$G$3:$H$20,2,FALSE()),0)) | P15: =IF(OR(N15="",O15="Closed",O15="Done - to verify"),"",N15-TODAY()) | Q15: =IF(C15="","",IF(O15="Closed","Closed",IF(O15="Done - to verify","To verify",IF(O15="On hold","On hold",IF(N15="","Set target",IF(N15<TODAY(),"OVERDUE",IF(N15-TODAY()<=7,"Due soon","On track")))))))
N16: =IF(OR(L16="",M16=""),"",L16+IFERROR(VLOOKUP(M16,Lists!$G$3:$H$20,2,FALSE()),0)) | P16: =IF(OR(N16="",O16="Closed",O16="Done - to verify"),"",N16-TODAY()) | Q16: =IF(C16="","",IF(O16="Closed","Closed",IF(O16="Done - to verify","To verify",IF(O16="On hold","On hold",IF(N16="","Set target",IF(N16<TODAY(),"OVERDUE",IF(N16-TODAY()<=7,"Due soon","On track")))))))
N17: =IF(OR(L17="",M17=""),"",L17+IFERROR(VLOOKUP(M17,Lists!$G$3:$H$20,2,FALSE()),0)) | P17: =IF(OR(N17="",O17="Closed",O17="Done - to verify"),"",N17-TODAY()) | Q17: =IF(C17="","",IF(O17="Closed","Closed",IF(O17="Done - to verify","To verify",IF(O17="On hold","On hold",IF(N17="","Set target",IF(N17<TODAY(),"OVERDUE",IF(N17-TODAY()<=7,"Due soon","On track")))))))
N18: =IF(OR(L18="",M18=""),"",L18+IFERROR(VLOOKUP(M18,Lists!$G$3:$H$20,2,FALSE()),0)) | P18: =IF(OR(N18="",O18="Closed",O18="Done - to verify"),"",N18-TODAY()) | Q18: =IF(C18="","",IF(O18="Closed","Closed",IF(O18="Done - to verify","To verify",IF(O18="On hold","On hold",IF(N18="","Set target",IF(N18<TODAY(),"OVERDUE",IF(N18-TODAY()<=7,"Due soon","On track")))))))
N19: =IF(OR(L19="",M19=""),"",L19+IFERROR(VLOOKUP(M19,Lists!$G$3:$H$20,2,FALSE()),0)) | P19: =IF(OR(N19="",O19="Closed",O19="Done - to verify"),"",N19-TODAY()) | Q19: =IF(C19="","",IF(O19="Closed","Closed",IF(O19="Done - to verify","To verify",IF(O19="On hold","On hold",IF(N19="","Set target",IF(N19<TODAY(),"OVERDUE",IF(N19-TODAY()<=7,"Due soon","On track")))))))
N20: =IF(OR(L20="",M20=""),"",L20+IFERROR(VLOOKUP(M20,Lists!$G$3:$H$20,2,FALSE()),0)) | P20: =IF(OR(N20="",O20="Closed",O20="Done - to verify"),"",N20-TODAY()) | Q20: =IF(C20="","",IF(O20="Closed","Closed",IF(O20="Done - to verify","To verify",IF(O20="On hold","On hold",IF(N20="","Set target",IF(N20<TODAY(),"OVERDUE",IF(N20-TODAY()<=7,"Due soon","On track")))))))
N21: =IF(OR(L21="",M21=""),"",L21+IFERROR(VLOOKUP(M21,Lists!$G$3:$H$20,2,FALSE()),0)) | P21: =IF(OR(N21="",O21="Closed",O21="Done - to verify"),"",N21-TODAY()) | Q21: =IF(C21="","",IF(O21="Closed","Closed",IF(O21="Done - to verify","To verify",IF(O21="On hold","On hold",IF(N21="","Set target",IF(N21<TODAY(),"OVERDUE",IF(N21-TODAY()<=7,"Due soon","On track")))))))
N22: =IF(OR(L22="",M22=""),"",L22+IFERROR(VLOOKUP(M22,Lists!$G$3:$H$20,2,FALSE()),0)) | P22: =IF(OR(N22="",O22="Closed",O22="Done - to verify"),"",N22-TODAY()) | Q22: =IF(C22="","",IF(O22="Closed","Closed",IF(O22="Done - to verify","To verify",IF(O22="On hold","On hold",IF(N22="","Set target",IF(N22<TODAY(),"OVERDUE",IF(N22-TODAY()<=7,"Due soon","On track")))))))
N23: =IF(OR(L23="",M23=""),"",L23+IFERROR(VLOOKUP(M23,Lists!$G$3:$H$20,2,FALSE()),0)) | P23: =IF(OR(N23="",O23="Closed",O23="Done - to verify"),"",N23-TODAY()) | Q23: =IF(C23="","",IF(O23="Closed","Closed",IF(O23="Done - to verify","To verify",IF(O23="On hold","On hold",IF(N23="","Set target",IF(N23<TODAY(),"OVERDUE",IF(N23-TODAY()<=7,"Due soon","On track")))))))
N24: =IF(OR(L24="",M24=""),"",L24+IFERROR(VLOOKUP(M24,Lists!$G$3:$H$20,2,FALSE()),0)) | P24: =IF(OR(N24="",O24="Closed",O24="Done - to verify"),"",N24-TODAY()) | Q24: =IF(C24="","",IF(O24="Closed","Closed",IF(O24="Done - to verify","To verify",IF(O24="On hold","On hold",IF(N24="","Set target",IF(N24<TODAY(),"OVERDUE",IF(N24-TODAY()<=7,"Due soon","On track")))))))
... N204: =IF(OR(L204="",M204=""),"",L204+IFERROR(VLOOKUP(M204,Lists!$G$3:$H$20,2,FALSE()),0)) | P204: =IF(OR(N204="",O204="Closed",O204="Done - to verify"),"",N204-TODAY()) | Q204: =IF(C204="","",IF(O204="Closed","Closed",IF(O204="Done - to verify","To verify",IF(O204="On hold","On hold",IF(N204="","Set target",IF(N204<TODAY(),"OVERDUE",IF(N204-TODAY()<=7,"Due soon","On track")))))))

Sheet Dashboard
A1: Dashboard: Mystery Shopper improvement points
A2: Updates automatically from the Tracker sheet. Nothing to type here.
A3: Today: | B3: =TODAY() -> 46294
A5: Total points | B5: Open | C5: In progress | D5: To verify | E5: Closed | F5: OVERDUE | G5: Due in 7 days | H5: % closed
A6: =COUNTA(Tracker!$C$5:$C$304) -> 8 | B6: =COUNTIF(Tracker!$O$5:$O$304,"Open") -> 8 | C6: =COUNTIF(Tracker!$O$5:$O$304,"In progress") -> 0 | D6: =COUNTIF(Tracker!$O$5:$O$304,"Done - to verify") -> 0 | E6: =COUNTIF(Tracker!$O$5:$O$304,"Closed") -> 0 | F6: =COUNTIF(Tracker!$Q$5:$Q$304,"OVERDUE") -> 0 | G6: =COUNTIF(Tracker!$Q$5:$Q$304,"Due soon") -> 0 | H6: =IF(A6=0,0,E6/A6) -> 0
A9: By outlet
A10: Outlet | B10: Total | C10: Open | D10: In progress | E10: To verify | F10: Closed | G10: OVERDUE | H10: % closed
A11: =IF(Lists!$A$3="","",Lists!$A$3) -> Greenlane | B11: =IF(A11="","",COUNTIF(Tracker!$B$5:$B$304,A11)) -> 1 | C11: =IF(A11="","",COUNTIFS(Tracker!$B$5:$B$304,A11,Tracker!$O$5:$O$304,"Open")) -> 1 | D11: =IF(A11="","",COUNTIFS(Tracker!$B$5:$B$304,A11,Tracker!$O$5:$O$304,"In progress")) -> 0 | E11: =IF(A11="","",COUNTIFS(Tracker!$B$5:$B$304,A11,Tracker!$O$5:$O$304,"Done - to verify")) -> 0 | F11: =IF(A11="","",COUNTIFS(Tracker!$B$5:$B$304,A11,Tracker!$O$5:$O$304,"Closed")) -> 0 | G11: =IF(A11="","",COUNTIFS(Tracker!$B$5:$B$304,A11,Tracker!$Q$5:$Q$304,"OVERDUE")) -> 0 | H11: =IF(OR(A11="",B11=0),"",F11/B11) -> 0
A12: =IF(Lists!$A$4="","",Lists!$A$4) -> Puchong | B12: =IF(A12="","",COUNTIF(Tracker!$B$5:$B$304,A12)) -> 0 | C12: =IF(A12="","",COUNTIFS(Tracker!$B$5:$B$304,A12,Tracker!$O$5:$O$304,"Open")) -> 0 | D12: =IF(A12="","",COUNTIFS(Tracker!$B$5:$B$304,A12,Tracker!$O$5:$O$304,"In progress")) -> 0 | E12: =IF(A12="","",COUNTIFS(Tracker!$B$5:$B$304,A12,Tracker!$O$5:$O$304,"Done - to verify")) -> 0 | F12: =IF(A12="","",COUNTIFS(Tracker!$B$5:$B$304,A12,Tracker!$O$5:$O$304,"Closed")) -> 0 | G12: =IF(A12="","",COUNTIFS(Tracker!$B$5:$B$304,A12,Tracker!$Q$5:$Q$304,"OVERDUE")) -> 0 | H12: =IF(OR(A12="",B12=0),"",F12/B12)
A13: =IF(Lists!$A$5="","",Lists!$A$5) -> Cheras Leisure Mall | B13: =IF(A13="","",COUNTIF(Tracker!$B$5:$B$304,A13)) -> 7 | C13: =IF(A13="","",COUNTIFS(Tracker!$B$5:$B$304,A13,Tracker!$O$5:$O$304,"Open")) -> 7 | D13: =IF(A13="","",COUNTIFS(Tracker!$B$5:$B$304,A13,Tracker!$O$5:$O$304,"In progress")) -> 0 | E13: =IF(A13="","",COUNTIFS(Tracker!$B$5:$B$304,A13,Tracker!$O$5:$O$304,"Done - to verify")) -> 0 | F13: =IF(A13="","",COUNTIFS(Tracker!$B$5:$B$304,A13,Tracker!$O$5:$O$304,"Closed")) -> 0 | G13: =IF(A13="","",COUNTIFS(Tracker!$B$5:$B$304,A13,Tracker!$Q$5:$Q$304,"OVERDUE")) -> 0 | H13: =IF(OR(A13="",B13=0),"",F13/B13) -> 0
A14: =IF(Lists!$A$6="","",Lists!$A$6) | B14: =IF(A14="","",COUNTIF(Tracker!$B$5:$B$304,A14)) | C14: =IF(A14="","",COUNTIFS(Tracker!$B$5:$B$304,A14,Tracker!$O$5:$O$304,"Open")) | D14: =IF(A14="","",COUNTIFS(Tracker!$B$5:$B$304,A14,Tracker!$O$5:$O$304,"In progress")) | E14: =IF(A14="","",COUNTIFS(Tracker!$B$5:$B$304,A14,Tracker!$O$5:$O$304,"Done - to verify")) | F14: =IF(A14="","",COUNTIFS(Tracker!$B$5:$B$304,A14,Tracker!$O$5:$O$304,"Closed")) | G14: =IF(A14="","",COUNTIFS(Tracker!$B$5:$B$304,A14,Tracker!$Q$5:$Q$304,"OVERDUE")) | H14: =IF(OR(A14="",B14=0),"",F14/B14)
A15: =IF(Lists!$A$7="","",Lists!$A$7) | B15: =IF(A15="","",COUNTIF(Tracker!$B$5:$B$304,A15)) | C15: =IF(A15="","",COUNTIFS(Tracker!$B$5:$B$304,A15,Tracker!$O$5:$O$304,"Open")) | D15: =IF(A15="","",COUNTIFS(Tracker!$B$5:$B$304,A15,Tracker!$O$5:$O$304,"In progress")) | E15: =IF(A15="","",COUNTIFS(Tracker!$B$5:$B$304,A15,Tracker!$O$5:$O$304,"Done - to verify")) | F15: =IF(A15="","",COUNTIFS(Tracker!$B$5:$B$304,A15,Tracker!$O$5:$O$304,"Closed")) | G15: =IF(A15="","",COUNTIFS(Tracker!$B$5:$B$304,A15,Tracker!$Q$5:$Q$304,"OVERDUE")) | H15: =IF(OR(A15="",B15=0),"",F15/B15)
A16: =IF(Lists!$A$8="","",Lists!$A$8) | B16: =IF(A16="","",COUNTIF(Tracker!$B$5:$B$304,A16)) | C16: =IF(A16="","",COUNTIFS(Tracker!$B$5:$B$304,A16,Tracker!$O$5:$O$304,"Open")) | D16: =IF(A16="","",COUNTIFS(Tracker!$B$5:$B$304,A16,Tracker!$O$5:$O$304,"In progress")) | E16: =IF(A16="","",COUNTIFS(Tracker!$B$5:$B$304,A16,Tracker!$O$5:$O$304,"Done - to verify")) | F16: =IF(A16="","",COUNTIFS(Tracker!$B$5:$B$304,A16,Tracker!$O$5:$O$304,"Closed")) | G16: =IF(A16="","",COUNTIFS(Tracker!$B$5:$B$304,A16,Tracker!$Q$5:$Q$304,"OVERDUE")) | H16: =IF(OR(A16="",B16=0),"",F16/B16)
A17: =IF(Lists!$A$9="","",Lists!$A$9) | B17: =IF(A17="","",COUNTIF(Tracker!$B$5:$B$304,A17)) | C17: =IF(A17="","",COUNTIFS(Tracker!$B$5:$B$304,A17,Tracker!$O$5:$O$304,"Open")) | D17: =IF(A17="","",COUNTIFS(Tracker!$B$5:$B$304,A17,Tracker!$O$5:$O$304,"In progress")) | E17: =IF(A17="","",COUNTIFS(Tracker!$B$5:$B$304,A17,Tracker!$O$5:$O$304,"Done - to verify")) | F17: =IF(A17="","",COUNTIFS(Tracker!$B$5:$B$304,A17,Tracker!$O$5:$O$304,"Closed")) | G17: =IF(A17="","",COUNTIFS(Tracker!$B$5:$B$304,A17,Tracker!$Q$5:$Q$304,"OVERDUE")) | H17: =IF(OR(A17="",B17=0),"",F17/B17)
A18: =IF(Lists!$A$10="","",Lists!$A$10) | B18: =IF(A18="","",COUNTIF(Tracker!$B$5:$B$304,A18)) | C18: =IF(A18="","",COUNTIFS(Tracker!$B$5:$B$304,A18,Tracker!$O$5:$O$304,"Open")) | D18: =IF(A18="","",COUNTIFS(Tracker!$B$5:$B$304,A18,Tracker!$O$5:$O$304,"In progress")) | E18: =IF(A18="","",COUNTIFS(Tracker!$B$5:$B$304,A18,Tracker!$O$5:$O$304,"Done - to verify")) | F18: =IF(A18="","",COUNTIFS(Tracker!$B$5:$B$304,A18,Tracker!$O$5:$O$304,"Closed")) | G18: =IF(A18="","",COUNTIFS(Tracker!$B$5:$B$304,A18,Tracker!$Q$5:$Q$304,"OVERDUE")) | H18: =IF(OR(A18="",B18=0),"",F18/B18)
A19: =IF(Lists!$A$11="","",Lists!$A$11) | B19: =IF(A19="","",COUNTIF(Tracker!$B$5:$B$304,A19)) | C19: =IF(A19="","",COUNTIFS(Tracker!$B$5:$B$304,A19,Tracker!$O$5:$O$304,"Open")) | D19: =IF(A19="","",COUNTIFS(Tracker!$B$5:$B$304,A19,Tracker!$O$5:$O$304,"In progress")) | E19: =IF(A19="","",COUNTIFS(Tracker!$B$5:$B$304,A19,Tracker!$O$5:$O$304,"Done - to verify")) | F19: =IF(A19="","",COUNTIFS(Tracker!$B$5:$B$304,A19,Tracker!$O$5:$O$304,"Closed")) | G19: =IF(A19="","",COUNTIFS(Tracker!$B$5:$B$304,A19,Tracker!$Q$5:$Q$304,"OVERDUE")) | H19: =IF(OR(A19="",B19=0),"",F19/B19)
A20: =IF(Lists!$A$12="","",Lists!$A$12) | B20: =IF(A20="","",COUNTIF(Tracker!$B$5:$B$304,A20)) | C20: =IF(A20="","",COUNTIFS(Tracker!$B$5:$B$304,A20,Tracker!$O$5:$O$304,"Open")) | D20: =IF(A20="","",COUNTIFS(Tracker!$B$5:$B$304,A20,Tracker!$O$5:$O$304,"In progress")) | E20: =IF(A20="","",COUNTIFS(Tracker!$B$5:$B$304,A20,Tracker!$O$5:$O$304,"Done - to verify")) | F20: =IF(A20="","",COUNTIFS(Tracker!$B$5:$B$304,A20,Tracker!$O$5:$O$304,"Closed")) | G20: =IF(A20="","",COUNTIFS(Tracker!$B$5:$B$304,A20,Tracker!$Q$5:$Q$304,"OVERDUE")) | H20: =IF(OR(A20="",B20=0),"",F20/B20)
A22: By priority
A23: Priority | B23: Total | C23: Open | D23: In progress | E23: To verify | F23: Closed | G23: OVERDUE | H23: % closed
A24: =IF(Lists!$D$3="","",Lists!$D$3) -> High | B24: =IF(A24="","",COUNTIF(Tracker!$I$5:$I$304,A24)) -> 4 | C24: =IF(A24="","",COUNTIFS(Tracker!$I$5:$I$304,A24,Tracker!$O$5:$O$304,"Open")) -> 4 | D24: =IF(A24="","",COUNTIFS(Tracker!$I$5:$I$304,A24,Tracker!$O$5:$O$304,"In progress")) -> 0 | E24: =IF(A24="","",COUNTIFS(Tracker!$I$5:$I$304,A24,Tracker!$O$5:$O$304,"Done - to verify")) -> 0 | F24: =IF(A24="","",COUNTIFS(Tracker!$I$5:$I$304,A24,Tracker!$O$5:$O$304,"Closed")) -> 0 | G24: =IF(A24="","",COUNTIFS(Tracker!$I$5:$I$304,A24,Tracker!$Q$5:$Q$304,"OVERDUE")) -> 0 | H24: =IF(OR(A24="",B24=0),"",F24/B24) -> 0
A25: =IF(Lists!$D$4="","",Lists!$D$4) -> Medium | B25: =IF(A25="","",COUNTIF(Tracker!$I$5:$I$304,A25)) -> 2 | C25: =IF(A25="","",COUNTIFS(Tracker!$I$5:$I$304,A25,Tracker!$O$5:$O$304,"Open")) -> 2 | D25: =IF(A25="","",COUNTIFS(Tracker!$I$5:$I$304,A25,Tracker!$O$5:$O$304,"In progress")) -> 0 | E25: =IF(A25="","",COUNTIFS(Tracker!$I$5:$I$304,A25,Tracker!$O$5:$O$304,"Done - to verify")) -> 0 | F25: =IF(A25="","",COUNTIFS(Tracker!$I$5:$I$304,A25,Tracker!$O$5:$O$304,"Closed")) -> 0 | G25: =IF(A25="","",COUNTIFS(Tracker!$I$5:$I$304,A25,Tracker!$Q$5:$Q$304,"OVERDUE")) -> 0 | H25: =IF(OR(A25="",B25=0),"",F25/B25) -> 0
A26: =IF(Lists!$D$5="","",Lists!$D$5) -> Low | B26: =IF(A26="","",COUNTIF(Tracker!$I$5:$I$304,A26)) -> 2 | C26: =IF(A26="","",COUNTIFS(Tracker!$I$5:$I$304,A26,Tracker!$O$5:$O$304,"Open")) -> 2 | D26: =IF(A26="","",COUNTIFS(Tracker!$I$5:$I$304,A26,Tracker!$O$5:$O$304,"In progress")) -> 0 | E26: =IF(A26="","",COUNTIFS(Tracker!$I$5:$I$304,A26,Tracker!$O$5:$O$304,"Done - to verify")) -> 0 | F26: =IF(A26="","",COUNTIFS(Tracker!$I$5:$I$304,A26,Tracker!$O$5:$O$304,"Closed")) -> 0 | G26: =IF(A26="","",COUNTIFS(Tracker!$I$5:$I$304,A26,Tracker!$Q$5:$Q$304,"OVERDUE")) -> 0 | H26: =IF(OR(A26="",B26=0),"",F26/B26) -> 0
A28: By category
A29: Category | B29: Total | C29: Open | D29: In progress | E29: To verify | F29: Closed | G29: OVERDUE | H29: % closed
A30: =IF(Lists!$C$3="","",Lists!$C$3) -> Sales & package | B30: =IF(A30="","",COUNTIF(Tracker!$E$5:$E$304,A30)) -> 2 | C30: =IF(A30="","",COUNTIFS(Tracker!$E$5:$E$304,A30,Tracker!$O$5:$O$304,"Open")) -> 2 | D30: =IF(A30="","",COUNTIFS(Tracker!$E$5:$E$304,A30,Tracker!$O$5:$O$304,"In progress")) -> 0 | E30: =IF(A30="","",COUNTIFS(Tracker!$E$5:$E$304,A30,Tracker!$O$5:$O$304,"Done - to verify")) -> 0 | F30: =IF(A30="","",COUNTIFS(Tracker!$E$5:$E$304,A30,Tracker!$O$5:$O$304,"Closed")) -> 0 | G30: =IF(A30="","",COUNTIFS(Tracker!$E$5:$E$304,A30,Tracker!$Q$5:$Q$304,"OVERDUE")) -> 0 | H30: =IF(OR(A30="",B30=0),"",F30/B30) -> 0
A31: =IF(Lists!$C$4="","",Lists!$C$4) -> Service attitude | B31: =IF(A31="","",COUNTIF(Tracker!$E$5:$E$304,A31)) -> 1 | C31: =IF(A31="","",COUNTIFS(Tracker!$E$5:$E$304,A31,Tracker!$O$5:$O$304,"Open")) -> 1 | D31: =IF(A31="","",COUNTIFS(Tracker!$E$5:$E$304,A31,Tracker!$O$5:$O$304,"In progress")) -> 0 | E31: =IF(A31="","",COUNTIFS(Tracker!$E$5:$E$304,A31,Tracker!$O$5:$O$304,"Done - to verify")) -> 0 | F31: =IF(A31="","",COUNTIFS(Tracker!$E$5:$E$304,A31,Tracker!$O$5:$O$304,"Closed")) -> 0 | G31: =IF(A31="","",COUNTIFS(Tracker!$E$5:$E$304,A31,Tracker!$Q$5:$Q$304,"OVERDUE")) -> 0 | H31: =IF(OR(A31="",B31=0),"",F31/B31) -> 0
A32: =IF(Lists!$C$5="","",Lists!$C$5) -> Communication | B32: =IF(A32="","",COUNTIF(Tracker!$E$5:$E$304,A32)) -> 1 | C32: =IF(A32="","",COUNTIFS(Tracker!$E$5:$E$304,A32,Tracker!$O$5:$O$304,"Open")) -> 1 | D32: =IF(A32="","",COUNTIFS(Tracker!$E$5:$E$304,A32,Tracker!$O$5:$O$304,"In progress")) -> 0 | E32: =IF(A32="","",COUNTIFS(Tracker!$E$5:$E$304,A32,Tracker!$O$5:$O$304,"Done - to verify")) -> 0 | F32: =IF(A32="","",COUNTIFS(Tracker!$E$5:$E$304,A32,Tracker!$O$5:$O$304,"Closed")) -> 0 | G32: =IF(A32="","",COUNTIFS(Tracker!$E$5:$E$304,A32,Tracker!$Q$5:$Q$304,"OVERDUE")) -> 0 | H32: =IF(OR(A32="",B32=0),"",F32/B32) -> 0
A33: =IF(Lists!$C$6="","",Lists!$C$6) -> Waiting & process flow | B33: =IF(A33="","",COUNTIF(Tracker!$E$5:$E$304,A33)) -> 1 | C33: =IF(A33="","",COUNTIFS(Tracker!$E$5:$E$304,A33,Tracker!$O$5:$O$304,"Open")) -> 1 | D33: =IF(A33="","",COUNTIFS(Tracker!$E$5:$E$304,A33,Tracker!$O$5:$O$304,"In progress")) -> 0 | E33: =IF(A33="","",COUNTIFS(Tracker!$E$5:$E$304,A33,Tracker!$O$5:$O$304,"Done - to verify")) -> 0 | F33: =IF(A33="","",COUNTIFS(Tracker!$E$5:$E$304,A33,Tracker!$O$5:$O$304,"Closed")) -> 0 | G33: =IF(A33="","",COUNTIFS(Tracker!$E$5:$E$304,A33,Tracker!$Q$5:$Q$304,"OVERDUE")) -> 0 | H33: =IF(OR(A33="",B33=0),"",F33/B33) -> 0
A34: =IF(Lists!$C$7="","",Lists!$C$7) -> Treatment & technique | B34: =IF(A34="","",COUNTIF(Tracker!$E$5:$E$304,A34)) -> 1 | C34: =IF(A34="","",COUNTIFS(Tracker!$E$5:$E$304,A34,Tracker!$O$5:$O$304,"Open")) -> 1 | D34: =IF(A34="","",COUNTIFS(Tracker!$E$5:$E$304,A34,Tracker!$O$5:$O$304,"In progress")) -> 0 | E34: =IF(A34="","",COUNTIFS(Tracker!$E$5:$E$304,A34,Tracker!$O$5:$O$304,"Done - to verify")) -> 0 | F34: =IF(A34="","",COUNTIFS(Tracker!$E$5:$E$304,A34,Tracker!$O$5:$O$304,"Closed")) -> 0 | G34: =IF(A34="","",COUNTIFS(Tracker!$E$5:$E$304,A34,Tracker!$Q$5:$Q$304,"OVERDUE")) -> 0 | H34: =IF(OR(A34="",B34=0),"",F34/B34) -> 0
A35: =IF(Lists!$C$8="","",Lists!$C$8) -> Appointment & reminder | B35: =IF(A35="","",COUNTIF(Tracker!$E$5:$E$304,A35)) -> 1 | C35: =IF(A35="","",COUNTIFS(Tracker!$E$5:$E$304,A35,Tracker!$O$5:$O$304,"Open")) -> 1 | D35: =IF(A35="","",COUNTIFS(Tracker!$E$5:$E$304,A35,Tracker!$O$5:$O$304,"In progress")) -> 0 | E35: =IF(A35="","",COUNTIFS(Tracker!$E$5:$E$304,A35,Tracker!$O$5:$O$304,"Done - to verify")) -> 0 | F35: =IF(A35="","",COUNTIFS(Tracker!$E$5:$E$304,A35,Tracker!$O$5:$O$304,"Closed")) -> 0 | G35: =IF(A35="","",COUNTIFS(Tracker!$E$5:$E$304,A35,Tracker!$Q$5:$Q$304,"OVERDUE")) -> 0 | H35: =IF(OR(A35="",B35=0),"",F35/B35) -> 0
A36: =IF(Lists!$C$9="","",Lists!$C$9) -> Registration & system | B36: =IF(A36="","",COUNTIF(Tracker!$E$5:$E$304,A36)) -> 1 | C36: =IF(A36="","",COUNTIFS(Tracker!$E$5:$E$304,A36,Tracker!$O$5:$O$304,"Open")) -> 1 | D36: =IF(A36="","",COUNTIFS(Tracker!$E$5:$E$304,A36,Tracker!$O$5:$O$304,"In progress")) -> 0 | E36: =IF(A36="","",COUNTIFS(Tracker!$E$5:$E$304,A36,Tracker!$O$5:$O$304,"Done - to verify")) -> 0 | F36: =IF(A36="","",COUNTIFS(Tracker!$E$5:$E$304,A36,Tracker!$O$5:$O$304,"Closed")) -> 0 | G36: =IF(A36="","",COUNTIFS(Tracker!$E$5:$E$304,A36,Tracker!$Q$5:$Q$304,"OVERDUE")) -> 0 | H36: =IF(OR(A36="",B36=0),"",F36/B36) -> 0
A37: =IF(Lists!$C$10="","",Lists!$C$10) -> Environment & facilities | B37: =IF(A37="","",COUNTIF(Tracker!$E$5:$E$304,A37)) -> 0 | C37: =IF(A37="","",COUNTIFS(Tracker!$E$5:$E$304,A37,Tracker!$O$5:$O$304,"Open")) -> 0 | D37: =IF(A37="","",COUNTIFS(Tracker!$E$5:$E$304,A37,Tracker!$O$5:$O$304,"In progress")) -> 0 | E37: =IF(A37="","",COUNTIFS(Tracker!$E$5:$E$304,A37,Tracker!$O$5:$O$304,"Done - to verify")) -> 0 | F37: =IF(A37="","",COUNTIFS(Tracker!$E$5:$E$304,A37,Tracker!$O$5:$O$304,"Closed")) -> 0 | G37: =IF(A37="","",COUNTIFS(Tracker!$E$5:$E$304,A37,Tracker!$Q$5:$Q$304,"OVERDUE")) -> 0 | H37: =IF(OR(A37="",B37=0),"",F37/B37)
A38: =IF(Lists!$C$11="","",Lists!$C$11) -> Others | B38: =IF(A38="","",COUNTIF(Tracker!$E$5:$E$304,A38)) -> 0 | C38: =IF(A38="","",COUNTIFS(Tracker!$E$5:$E$304,A38,Tracker!$O$5:$O$304,"Open")) -> 0 | D38: =IF(A38="","",COUNTIFS(Tracker!$E$5:$E$304,A38,Tracker!$O$5:$O$304,"In progress")) -> 0 | E38: =IF(A38="","",COUNTIFS(Tracker!$E$5:$E$304,A38,Tracker!$O$5:$O$304,"Done - to verify")) -> 0 | F38: =IF(A38="","",COUNTIFS(Tracker!$E$5:$E$304,A38,Tracker!$O$5:$O$304,"Closed")) -> 0 | G38: =IF(A38="","",COUNTIFS(Tracker!$E$5:$E$304,A38,Tracker!$Q$5:$Q$304,"OVERDUE")) -> 0 | H38: =IF(OR(A38="",B38=0),"",F38/B38)
A39: =IF(Lists!$C$12="","",Lists!$C$12) | B39: =IF(A39="","",COUNTIF(Tracker!$E$5:$E$304,A39)) | C39: =IF(A39="","",COUNTIFS(Tracker!$E$5:$E$304,A39,Tracker!$O$5:$O$304,"Open")) | D39: =IF(A39="","",COUNTIFS(Tracker!$E$5:$E$304,A39,Tracker!$O$5:$O$304,"In progress")) | E39: =IF(A39="","",COUNTIFS(Tracker!$E$5:$E$304,A39,Tracker!$O$5:$O$304,"Done - to verify")) | F39: =IF(A39="","",COUNTIFS(Tracker!$E$5:$E$304,A39,Tracker!$O$5:$O$304,"Closed")) | G39: =IF(A39="","",COUNTIFS(Tracker!$E$5:$E$304,A39,Tracker!$Q$5:$Q$304,"OVERDUE")) | H39: =IF(OR(A39="",B39=0),"",F39/B39)
A40: =IF(Lists!$C$13="","",Lists!$C$13) | B40: =IF(A40="","",COUNTIF(Tracker!$E$5:$E$304,A40)) | C40: =IF(A40="","",COUNTIFS(Tracker!$E$5:$E$304,A40,Tracker!$O$5:$O$304,"Open")) | D40: =IF(A40="","",COUNTIFS(Tracker!$E$5:$E$304,A40,Tracker!$O$5:$O$304,"In progress")) | E40: =IF(A40="","",COUNTIFS(Tracker!$E$5:$E$304,A40,Tracker!$O$5:$O$304,"Done - to verify")) | F40: =IF(A40="","",COUNTIFS(Tracker!$E$5:$E$304,A40,Tracker!$O$5:$O$304,"Closed")) | G40: =IF(A40="","",COUNTIFS(Tracker!$E$5:$E$304,A40,Tracker!$Q$5:$Q$304,"OVERDUE")) | H40: =IF(OR(A40="",B40=0),"",F40/B40)
A41: =IF(Lists!$C$14="","",Lists!$C$14) | B41: =IF(A41="","",COUNTIF(Tracker!$E$5:$E$304,A41)) | C41: =IF(A41="","",COUNTIFS(Tracker!$E$5:$E$304,A41,Tracker!$O$5:$O$304,"Open")) | D41: =IF(A41="","",COUNTIFS(Tracker!$E$5:$E$304,A41,Tracker!$O$5:$O$304,"In progress")) | E41: =IF(A41="","",COUNTIFS(Tracker!$E$5:$E$304,A41,Tracker!$O$5:$O$304,"Done - to verify")) | F41: =IF(A41="","",COUNTIFS(Tracker!$E$5:$E$304,A41,Tracker!$O$5:$O$304,"Closed")) | G41: =IF(A41="","",COUNTIFS(Tracker!$E$5:$E$304,A41,Tracker!$Q$5:$Q$304,"OVERDUE")) | H41: =IF(OR(A41="",B41=0),"",F41/B41)

Sheet MS Reports
A1: Mystery Shopper reports received
A2: Log every report here when it arrives, then copy its improvement points into the Tracker. Grey columns are automatic.
A4: Report ID | B4: MS report (month) | C4: Outlet | D4: Visit date | E4: Score (as reported) | F4: Would return / recommend? | G4: Points logged (auto) | H4: Points closed (auto) | I4: Staff named in report | J4: Report file | K4: Reviewed at meeting | L4: Notes
A5: MS-2609-CLM | B5: Sep 2026 | C5: Cheras Leisure Mall | E5: 93 | F5: Maybe / Yes. Price is expensive, but may return for pigmentation treatment. | G5: =IF(C5="","",COUNTIFS(Tracker!$B$5:$B$304,C5,Tracker!$D$5:$D$304,B5)) -> 7 | H5: =IF(C5="","",COUNTIFS(Tracker!$B$5:$B$304,C5,Tracker!$D$5:$D$304,B5,Tracker!$O$5:$O$304,"Closed")) -> 0 | I5: Dr. Agnes Lu, Alice, Ng Kai Wei, Irene | J5: MS result sheet (Sep, Cheras Leisure Mall row) + UR_Klinik_Mystery_Shopper_Cheras_Leisure_Mall_September_Feedback_Appendix.pptx | L5: Main theme: package presentation felt too commercial; long waiting; treatment steps not clear.
A6: MS-2609-GL | B6: Sep 2026 | C6: Greenlane | E6: 60 | F6: Maybe / Maybe / Still considering… | G6: =IF(C6="","",COUNTIFS(Tracker!$B$5:$B$304,C6,Tracker!$D$5:$D$304,B6)) -> 1 | H6: =IF(C6="","",COUNTIFS(Tracker!$B$5:$B$304,C6,Tracker!$D$5:$D$304,B6,Tracker!$O$5:$O$304,"Closed")) -> 0 | I6: Dr Michelle, Stella, Karene, Graceyy | J6: MS result sheet (Sep, Greenlane row) + customer's WhatsApp follow-up, 15/09/2026 | L6: Customer's follow-up: the main issue was staff attitude, not only the selling. Staff mentioned in the QA chat: Dr Michelle and Stella.
G7: =IF(C7="","",COUNTIFS(Tracker!$B$5:$B$304,C7,Tracker!$D$5:$D$304,B7)) | H7: =IF(C7="","",COUNTIFS(Tracker!$B$5:$B$304,C7,Tracker!$D$5:$D$304,B7,Tracker!$O$5:$O$304,"Closed"))
G8: =IF(C8="","",COUNTIFS(Tracker!$B$5:$B$304,C8,Tracker!$D$5:$D$304,B8)) | H8: =IF(C8="","",COUNTIFS(Tracker!$B$5:$B$304,C8,Tracker!$D$5:$D$304,B8,Tracker!$O$5:$O$304,"Closed"))
G9: =IF(C9="","",COUNTIFS(Tracker!$B$5:$B$304,C9,Tracker!$D$5:$D$304,B9)) | H9: =IF(C9="","",COUNTIFS(Tracker!$B$5:$B$304,C9,Tracker!$D$5:$D$304,B9,Tracker!$O$5:$O$304,"Closed"))
G10: =IF(C10="","",COUNTIFS(Tracker!$B$5:$B$304,C10,Tracker!$D$5:$D$304,B10)) | H10: =IF(C10="","",COUNTIFS(Tracker!$B$5:$B$304,C10,Tracker!$D$5:$D$304,B10,Tracker!$O$5:$O$304,"Closed"))
G11: =IF(C11="","",COUNTIFS(Tracker!$B$5:$B$304,C11,Tracker!$D$5:$D$304,B11)) | H11: =IF(C11="","",COUNTIFS(Tracker!$B$5:$B$304,C11,Tracker!$D$5:$D$304,B11,Tracker!$O$5:$O$304,"Closed"))
G12: =IF(C12="","",COUNTIFS(Tracker!$B$5:$B$304,C12,Tracker!$D$5:$D$304,B12)) | H12: =IF(C12="","",COUNTIFS(Tracker!$B$5:$B$304,C12,Tracker!$D$5:$D$304,B12,Tracker!$O$5:$O$304,"Closed"))
G13: =IF(C13="","",COUNTIFS(Tracker!$B$5:$B$304,C13,Tracker!$D$5:$D$304,B13)) | H13: =IF(C13="","",COUNTIFS(Tracker!$B$5:$B$304,C13,Tracker!$D$5:$D$304,B13,Tracker!$O$5:$O$304,"Closed"))
G14: =IF(C14="","",COUNTIFS(Tracker!$B$5:$B$304,C14,Tracker!$D$5:$D$304,B14)) | H14: =IF(C14="","",COUNTIFS(Tracker!$B$5:$B$304,C14,Tracker!$D$5:$D$304,B14,Tracker!$O$5:$O$304,"Closed"))
G15: =IF(C15="","",COUNTIFS(Tracker!$B$5:$B$304,C15,Tracker!$D$5:$D$304,B15)) | H15: =IF(C15="","",COUNTIFS(Tracker!$B$5:$B$304,C15,Tracker!$D$5:$D$304,B15,Tracker!$O$5:$O$304,"Closed"))
G16: =IF(C16="","",COUNTIFS(Tracker!$B$5:$B$304,C16,Tracker!$D$5:$D$304,B16)) | H16: =IF(C16="","",COUNTIFS(Tracker!$B$5:$B$304,C16,Tracker!$D$5:$D$304,B16,Tracker!$O$5:$O$304,"Closed"))
G17: =IF(C17="","",COUNTIFS(Tracker!$B$5:$B$304,C17,Tracker!$D$5:$D$304,B17)) | H17: =IF(C17="","",COUNTIFS(Tracker!$B$5:$B$304,C17,Tracker!$D$5:$D$304,B17,Tracker!$O$5:$O$304,"Closed"))
G18: =IF(C18="","",COUNTIFS(Tracker!$B$5:$B$304,C18,Tracker!$D$5:$D$304,B18)) | H18: =IF(C18="","",COUNTIFS(Tracker!$B$5:$B$304,C18,Tracker!$D$5:$D$304,B18,Tracker!$O$5:$O$304,"Closed"))
... G44: =IF(C44="","",COUNTIFS(Tracker!$B$5:$B$304,C44,Tracker!$D$5:$D$304,B44)) | H44: =IF(C44="","",COUNTIFS(Tracker!$B$5:$B$304,C44,Tracker!$D$5:$D$304,B44,Tracker!$O$5:$O$304,"Closed"))

Sheet Meeting Log
A1: Review meeting log
A2: One row per review meeting: this is your record for the next audit.
A4: Meeting date | B4: Attendees | C4: Tracker IDs reviewed | D4: Decisions / key notes | E4: Next review date
C5: MS-2609-CLM-01 to 07, MS-2609-GL-01

Sheet Lists
A1: Dropdown lists: add new outlets, categories or PIC names in the empty cells below each list.
A2: Outlets | B2: Outlet code (for ID) | C2: Categories | D2: Priority | E2: Status | F2: PIC (person in charge) | G2: Timeline | H2: Days
A3: Greenlane | B3: GL | C3: Sales & package | D3: High | E3: Open | F3: Outlet Manager | G3: 1 week | H3: 7
A4: Puchong | B4: PC | C4: Service attitude | D4: Medium | E4: In progress | F4: Front Desk / CS | G4: 2 weeks | H4: 14
A5: Cheras Leisure Mall | B5: CLM | C5: Communication | D5: Low | E5: Done - to verify | F5: Doctor | G5: 1 month | H5: 30
C6: Waiting & process flow | E6: Closed | F6: Therapist Lead | G6: 2 months | H6: 60
C7: Treatment & technique | E7: On hold | F7: Sales / Consultant | G7: 3 months | H7: 90
C8: Appointment & reminder | F8: QA
C9: Registration & system
C10: Environment & facilities
C11: Others
